{
    "AX": {
        "error": 0.006415261536970908,
        "filter_outliers_dict": {
            "filter_outliers": true,
            "iterations": 1,
            "std_devs": 2,
            "use_iqr_filtering": false,
            "use_standard_deviation_filtering": false
        },
        "fit": "Average",
        "fn": 58,
        "include_baseline_error": false,
        "n": 60,
        "outlier_excluded": [
            33,
            18
        ],
        "reviewed": true,
        "user_excluded": [],
        "value": -0.0679805019252195
    },
    "CDD": {
        "error": 2.2434905420032185e-05,
        "filter_outliers_dict": {
            "filter_outliers": true,
            "iterations": 1,
            "std_devs": 10,
            "use_iqr_filtering": false,
            "use_standard_deviation_filtering": false
        },
        "fit": "Average",
        "fn": 60,
        "include_baseline_error": false,
        "n": 60,
        "outlier_excluded": [],
        "reviewed": true,
        "user_excluded": [],
        "value": 0.000235437489754986
    },
    "H1": {
        "error": 0.0062717662737015465,
        "filter_outliers_dict": {
            "filter_outliers": true,
            "iterations": 1,
            "std_devs": 2,
            "use_iqr_filtering": false,
            "use_standard_deviation_filtering": false
        },
        "fit": "Average",
        "fn": 58,
        "include_baseline_error": false,
        "n": 60,
        "outlier_excluded": [
            0,
            30
        ],
        "reviewed": true,
        "user_excluded": [],
        "value": 0.11388944853739492
    },
    "H2": {
        "error": 0.004022029788281568,
        "filter_outliers_dict": {
            "filter_outliers": true,
            "iterations": 1,
            "std_devs": 2
        },
        "fit": "average",
        "value": -0.07179133081644432
    },
    "L1": {
        "error": 0.003301380859229875,
        "filter_outliers_dict": {
            "filter_outliers": true,
            "iterations": 1,
            "std_devs": 2,
            "use_iqr_filtering": false,
            "use_standard_deviation_filtering": false
        },
        "fit": "Average",
        "fn": 59,
        "include_baseline_error": false,
        "n": 60,
        "outlier_excluded": [
            54
        ],
        "reviewed": true,
        "user_excluded": [],
        "value": -0.028165584733962256
    },
    "L2": {
        "error": 0.005583711745519478,
        "filter_outliers_dict": {
            "filter_outliers": true,
            "iterations": 1,
            "std_devs": 2,
            "use_iqr_filtering": false,
            "use_standard_deviation_filtering": false
        },
        "fit": "Average",
        "fn": 57,
        "include_baseline_error": false,
        "n": 60,
        "outlier_excluded": [
            24,
            33,
            39
        ],
        "reviewed": true,
        "user_excluded": [],
        "value": -0.029836265436626905
    }
}