{
    "Ar36": {
        "error": 0.0002403961975024411,
        "filter_outliers_dict": {
            "filter_outliers": true,
            "iterations": 1,
            "std_devs": 2,
            "use_iqr_filtering": false,
            "use_standard_deviation_filtering": false
        },
        "fit": "Linear",
        "fn": 116,
        "include_baseline_error": false,
        "n": 120,
        "outlier_excluded": [
            0,
            3,
            107,
            61
        ],
        "reviewed": true,
        "user_excluded": [],
        "value": 0.006754994704631931
    },
    "Ar37": {
        "error": 0.010584527147796646,
        "filter_outliers_dict": {
            "filter_outliers": true,
            "iterations": 1,
            "std_devs": 2,
            "use_iqr_filtering": false,
            "use_standard_deviation_filtering": false
        },
        "fit": "Linear",
        "fn": 118,
        "include_baseline_error": false,
        "n": 120,
        "outlier_excluded": [
            57,
            69
        ],
        "reviewed": true,
        "user_excluded": [],
        "value": 0.2966642424821173
    },
    "Ar38": {
        "error": 0.004485792121745902,
        "filter_outliers_dict": {
            "filter_outliers": true,
            "iterations": 1,
            "std_devs": 2,
            "use_iqr_filtering": false,
            "use_standard_deviation_filtering": false
        },
        "fit": "Linear",
        "fn": 116,
        "include_baseline_error": false,
        "n": 120,
        "outlier_excluded": [
            0,
            1,
            112,
            53
        ],
        "reviewed": true,
        "user_excluded": [],
        "value": 0.14164497521976394
    },
    "Ar39": {
        "error": 0.0140193652976854,
        "filter_outliers_dict": {
            "filter_outliers": true,
            "iterations": 1,
            "std_devs": 2,
            "use_iqr_filtering": false,
            "use_standard_deviation_filtering": false
        },
        "fit": "Linear",
        "fn": 115,
        "include_baseline_error": false,
        "n": 120,
        "outlier_excluded": [
            18,
            83,
            12,
            46,
            70
        ],
        "reviewed": true,
        "user_excluded": [],
        "value": 12.959765400843068
    },
    "Ar40": {
        "error": 0.015811113601903636,
        "filter_outliers_dict": {
            "filter_outliers": true,
            "iterations": 1,
            "std_devs": 2,
            "use_iqr_filtering": false,
            "use_standard_deviation_filtering": false
        },
        "fit": "Linear",
        "fn": 117,
        "include_baseline_error": false,
        "n": 120,
        "outlier_excluded": [
            115,
            44,
            47
        ],
        "reviewed": true,
        "user_excluded": [],
        "value": 63.823144138691205
    },
    "Ar41": {
        "error": 0.004911110886951192,
        "filter_outliers_dict": {
            "filter_outliers": true,
            "iterations": 1,
            "std_devs": 2
        },
        "fit": "Average",
        "fn": 113,
        "include_baseline_error": false,
        "n": 120,
        "value": -0.18182330895050436
    },
    "reviewed": true
}