{
    "Ar36": {
        "error": 0.001721968248749789, 
        "filter_outliers_dict": {
            "filter_outliers": true, 
            "iterations": 1, 
            "std_devs": 10
        }, 
        "fit": "Linear", 
        "fn": 120, 
        "include_baseline_error": false, 
        "n": 120, 
        "value": 0.39891730049544466
    }, 
    "Ar37": {
        "error": 0.010446681567558198, 
        "filter_outliers_dict": {
            "filter_outliers": true, 
            "iterations": 1, 
            "std_devs": 2
        }, 
        "fit": "Linear", 
        "fn": 114, 
        "include_baseline_error": false, 
        "n": 120, 
        "value": 1.2506977448335297
    }, 
    "Ar38": {
        "error": 0.004774447144228485, 
        "filter_outliers_dict": {
            "filter_outliers": true, 
            "iterations": 1, 
            "std_devs": 2
        }, 
        "fit": "Linear", 
        "fn": 115, 
        "include_baseline_error": false, 
        "n": 120, 
        "value": 0.9159017088594921
    }, 
    "Ar39": {
        "error": 0.019162671282942023, 
        "filter_outliers_dict": {
            "filter_outliers": true, 
            "iterations": 1, 
            "std_devs": 2
        }, 
        "fit": "Linear", 
        "fn": 118, 
        "include_baseline_error": false, 
        "n": 120, 
        "value": 64.16379790689768
    }, 
    "Ar40": {
        "error": 0.029921123825988924, 
        "filter_outliers_dict": {
            "filter_outliers": true, 
            "iterations": 1, 
            "std_devs": 2
        }, 
        "fit": "Linear", 
        "fn": 114, 
        "include_baseline_error": false, 
        "n": 120, 
        "value": 315.59032909401606
    }, 
    "Ar41": {
        "error": 0.00656107852519074, 
        "filter_outliers_dict": {
            "filter_outliers": true, 
            "iterations": 1, 
            "std_devs": 2
        }, 
        "fit": "Average", 
        "fn": 115, 
        "include_baseline_error": false, 
        "n": 120, 
        "value": -0.15672288748597646
    }, 
    "reviewed": true
}