{
    "Ar36": {
        "error": 0.00018436523831522823,
        "filter_outliers_dict": {
            "filter_outliers": true,
            "iterations": 1,
            "std_devs": 2,
            "use_iqr_filtering": false,
            "use_standard_deviation_filtering": false
        },
        "fit": "Parabolic",
        "fn": 388,
        "include_baseline_error": false,
        "n": 400,
        "outlier_excluded": [
            0,
            192,
            321,
            235,
            364,
            399,
            272,
            50,
            182,
            374,
            121,
            379
        ],
        "reviewed": true,
        "user_excluded": [],
        "value": 0.005662012971493401
    },
    "Ar37": {
        "error": 0.0051965622140582295,
        "filter_outliers_dict": {
            "filter_outliers": true,
            "iterations": 1,
            "std_devs": 2,
            "use_iqr_filtering": false,
            "use_standard_deviation_filtering": false
        },
        "fit": "Linear",
        "fn": 382,
        "include_baseline_error": false,
        "n": 400,
        "outlier_excluded": [
            225,
            130,
            3,
            4,
            36,
            162,
            291,
            104,
            391,
            330,
            302,
            398,
            304,
            210,
            24,
            280,
            344,
            94
        ],
        "reviewed": true,
        "user_excluded": [],
        "value": 0.025705770665026995
    },
    "Ar38": {
        "error": 0.0022125142558575873,
        "filter_outliers_dict": {
            "filter_outliers": true,
            "iterations": 1,
            "std_devs": 2,
            "use_iqr_filtering": false,
            "use_standard_deviation_filtering": false
        },
        "fit": "Linear",
        "fn": 384,
        "include_baseline_error": false,
        "n": 400,
        "outlier_excluded": [
            386,
            3,
            68,
            164,
            326,
            231,
            136,
            397,
            14,
            206,
            80,
            17,
            18,
            144,
            308,
            184
        ],
        "reviewed": true,
        "user_excluded": [],
        "value": -0.02034605079974054
    },
    "Ar39": {
        "error": 0.009103722567478977,
        "filter_outliers_dict": {
            "filter_outliers": true,
            "iterations": 1,
            "std_devs": 2,
            "use_iqr_filtering": false,
            "use_standard_deviation_filtering": false
        },
        "fit": "Parabolic",
        "fn": 382,
        "include_baseline_error": false,
        "n": 400,
        "outlier_excluded": [
            0,
            1,
            162,
            256,
            72,
            265,
            10,
            203,
            110,
            81,
            273,
            147,
            179,
            370,
            57,
            377,
            187,
            319
        ],
        "reviewed": true,
        "user_excluded": [],
        "value": -0.023964410798382765
    },
    "Ar40": {
        "error": 0.007364398076818771,
        "filter_outliers_dict": {
            "filter_outliers": true,
            "iterations": 1,
            "std_devs": 2,
            "use_iqr_filtering": false,
            "use_standard_deviation_filtering": false
        },
        "fit": "Parabolic",
        "fn": 380,
        "include_baseline_error": false,
        "n": 400,
        "outlier_excluded": [
            157,
            190,
            2,
            67,
            68,
            101,
            225,
            7,
            384,
            41,
            266,
            11,
            205,
            177,
            210,
            277,
            246,
            29,
            125,
            31
        ],
        "reviewed": true,
        "user_excluded": [],
        "value": 0.7648469883149873
    },
    "Ar41": {
        "error": 0.002905603433741323,
        "filter_outliers_dict": {
            "filter_outliers": true,
            "iterations": 1,
            "std_devs": 2
        },
        "fit": "Average",
        "fn": 380,
        "include_baseline_error": false,
        "n": 400,
        "value": -0.18553029990902073
    },
    "reviewed": true
}